{
  "profile": {
    "uuid": "0e8224ee-8217-5cac-b5e0-23f8822f2204",
    "metadata": {
      "title": "Google Android 15 COBO Security Technical Implementation Guide \u2013 II - Mission Support Sensitive",
      "last-modified": "2025-01-30T00:00:00Z",
      "version": "1.2.0",
      "oscal-version": "1.1.3",
      "remarks": "This Security Technical Implementation Guide is published as a tool to improve the security of Department of Defense (DOD) information systems. The requirements are derived from the National Institute of Standards and Technology (NIST) 800-53 and related documents. Comments or proposed revisions to this document should be sent via email to the following address: disa.stig_spt@mail.mil."
    },
    "imports": [
      {
        "href": "https://raw.githubusercontent.com/bionicspy/oscal-content/refs/heads/main/catalogs/disa-stig-google-android-15-cobo-v1r2/catalog.json",
        "include-controls": [
          {
            "with-ids": [
              "SV-267430r1031475_rule",
              "SV-267431r1031478_rule",
              "SV-267432r1031481_rule",
              "SV-267433r1031484_rule",
              "SV-267434r1033027_rule",
              "SV-267435r1031490_rule",
              "SV-267436r1033112_rule",
              "SV-267437r1033032_rule",
              "SV-267438r1042520_rule",
              "SV-267439r1031502_rule",
              "SV-267440r1031505_rule",
              "SV-267441r1033036_rule",
              "SV-267442r1031511_rule",
              "SV-267443r1031514_rule",
              "SV-267444r1031517_rule",
              "SV-267445r1031520_rule",
              "SV-267446r1031523_rule",
              "SV-267447r1033115_rule",
              "SV-267448r1033039_rule",
              "SV-267449r1031532_rule",
              "SV-267450r1042523_rule",
              "SV-267451r1033041_rule",
              "SV-267452r1031541_rule",
              "SV-267453r1031544_rule",
              "SV-267454r1031547_rule",
              "SV-267455r1033044_rule",
              "SV-267456r1031553_rule",
              "SV-267457r1031556_rule",
              "SV-267458r1031559_rule",
              "SV-267459r1031562_rule",
              "SV-267460r1033046_rule",
              "SV-267461r1031568_rule",
              "SV-267462r1033049_rule",
              "SV-267463r1033052_rule",
              "SV-267464r1033054_rule",
              "SV-269100r1033116_rule"
            ]
          }
        ]
      }
    ]
  }
}